{
	"configurations" : 
	[
		{
			"directories" : 
			[
				{
					"build" : ".",
					"hasInstallRule" : true,
					"jsonFile" : "directory-.-Debug-6f4404f4dee2cb085150.json",
					"minimumCMakeVersion" : 
					{
						"string" : "3.16"
					},
					"projectIndex" : 0,
					"source" : ".",
					"targetIndexes" : 
					[
						0,
						1,
						2
					]
				}
			],
			"name" : "Debug",
			"projects" : 
			[
				{
					"directoryIndexes" : 
					[
						0
					],
					"name" : "HelloUser",
					"targetIndexes" : 
					[
						0,
						1,
						2
					]
				}
			],
			"targets" : 
			[
				{
					"directoryIndex" : 0,
					"id" : "HelloUser::@6890427a1f51a3e7e1df",
					"jsonFile" : "target-HelloUser-Debug-d065f139b85443df7564.json",
					"name" : "HelloUser",
					"projectIndex" : 0
				},
				{
					"directoryIndex" : 0,
					"id" : "HelloUser_autogen::@6890427a1f51a3e7e1df",
					"jsonFile" : "target-HelloUser_autogen-Debug-a7c38e3e760fea561deb.json",
					"name" : "HelloUser_autogen",
					"projectIndex" : 0
				},
				{
					"directoryIndex" : 0,
					"id" : "HelloUser_autogen_timestamp_deps::@6890427a1f51a3e7e1df",
					"jsonFile" : "target-HelloUser_autogen_timestamp_deps-Debug-1a9974552d475f7f9163.json",
					"name" : "HelloUser_autogen_timestamp_deps",
					"projectIndex" : 0
				}
			]
		}
	],
	"kind" : "codemodel",
	"paths" : 
	{
		"build" : "/home/ehayes/HelloUser/build/Desktop_Qt_6_10_1-Debug",
		"source" : "/home/ehayes/HelloUser"
	},
	"version" : 
	{
		"major" : 2,
		"minor" : 7
	}
}
